blosum/__init__.py
blosum/_blosum.py
blosum/_data.py
blosum-2.0.3.dist-info/LICENSE
blosum-2.0.3.dist-info/METADATA
blosum-2.0.3.dist-info/WHEEL
blosum-2.0.3.dist-info/top_level.txt
blosum-2.0.3.dist-info/RECORD
