Metadata-Version: 2.1
Name: blosum
Version: 2.0.3
Summary: A simple BLOSUM toolbox without dependencies.
Home-page: https://github.com/not-a-feature/blosum
Author: Jules Kreuer / not_a_feature
License: gpl-3.0
Keywords: BLOSUM,reader,bio,bioinformatics,blosum62,blosum45,blosum50,blosum90
Platform: unix
Platform: linux
Platform: osx
Platform: cygwin
Platform: win32
Classifier: Programming Language :: Python :: 3
Requires-Python: >=3.8
License-File: LICENSE
Provides-Extra: testing
Requires-Dist: pytest >=6.0 ; extra == 'testing'
Requires-Dist: pytest-cov >=2.0 ; extra == 'testing'
Requires-Dist: tox >=3.20 ; extra == 'testing'
